src/WidgetPictureGenerator.py
src/__init__.py
src/main.py
widget_picture_generator/__init__.py
widget_picture_generator-0.0.6.dist-info/LICENSE
widget_picture_generator-0.0.6.dist-info/METADATA
widget_picture_generator-0.0.6.dist-info/WHEEL
widget_picture_generator-0.0.6.dist-info/top_level.txt
widget_picture_generator-0.0.6.dist-info/RECORD
