Metadata-Version: 2.1
Name: widget-picture-generator
Version: 0.0.6
Summary: This library can be used to generate high-quality images of any type of widget, such as charts, maps, and leaderboards
Home-page: https://github.com/Sense-Square/widget-picture-generator
Author: Massimo Moffa
Author-email: massimo.moffa@sensesquare.eu
Classifier: Programming Language :: Python :: 3
Classifier: License :: OSI Approved :: MIT License
Classifier: Operating System :: OS Independent
License-File: LICENSE
Requires-Dist: selenium
